schnittstelle/__init__.py
schnittstelle/item.py
schnittstelle/line.py
schnittstelle/runnable.py
schnittstelle/colorize/__init__.py
schnittstelle/completer/__init__.py
schnittstelle/completer/style.py
schnittstelle/decorators/__init__.py
schnittstelle/loader/__init__.py
schnittstelle/loader/drawing.py
schnittstelle/loader/loader.py
schnittstelle/loader/style.py
schnittstelle/unicode/__init__.py
schnittstelle-0.1.0.dist-info/LICENSE
schnittstelle-0.1.0.dist-info/METADATA
schnittstelle-0.1.0.dist-info/WHEEL
schnittstelle-0.1.0.dist-info/top_level.txt
schnittstelle-0.1.0.dist-info/RECORD
