Metadata-Version: 2.1
Name: schnittstelle
Version: 0.1.0
Summary: A console ui interface
Home-page: https://github.com/mHaisham/schnittstelle
Author: Schicksal
Author-email: mhaisham79@gmail.com
License: MIT license
Project-URL: Source code, https://github.com/mHaisham/schnittstelle
Keywords: console interface progress
Platform: UNKNOWN
Classifier: License :: OSI Approved :: MIT License
Classifier: Programming Language :: Python :: 3.7
Classifier: Operating System :: OS Independent
Requires-Python: >=3.6
Requires-Dist: colorama
